discord/ext/listening/__init__.py
discord/ext/listening/enums.py
discord/ext/listening/gateway.py
discord/ext/listening/opus.py
discord/ext/listening/processing.py
discord/ext/listening/sink.py
discord/ext/listening/voice_client.py
discord_ext_listening-0.0.3.dist-info/LICENSE
discord_ext_listening-0.0.3.dist-info/METADATA
discord_ext_listening-0.0.3.dist-info/WHEEL
discord_ext_listening-0.0.3.dist-info/top_level.txt
discord_ext_listening-0.0.3.dist-info/RECORD
