Metadata-Version: 2.1
Name: discord-ext-listening
Version: 0.0.3
Summary: Voice receive extension for discord.py built on multiprocessing and designed to be flexible.
Home-page: https://github.com/sheppsu/discord-ext-listening
Author: Sheppsu
License: MIT
Classifier: License :: OSI Approved :: MIT License
Classifier: Intended Audience :: Developers
Classifier: Natural Language :: English
Classifier: Operating System :: OS Independent
Classifier: Programming Language :: Python :: 3.8
Classifier: Programming Language :: Python :: 3.9
Classifier: Programming Language :: Python :: 3.10
Classifier: Programming Language :: Python :: 3.11
Classifier: Topic :: Multimedia :: Sound/Audio :: Capture/Recording
Requires-Python: >=3.8.0
License-File: LICENSE
Requires-Dist: discord.py[voice] (>=2.2.0)
